README.md
setup.py
jaxxstorm_pulumi_awsloadbalancercontroller/__init__.py
jaxxstorm_pulumi_awsloadbalancercontroller/_utilities.py
jaxxstorm_pulumi_awsloadbalancercontroller/deployment.py
jaxxstorm_pulumi_awsloadbalancercontroller/provider.py
jaxxstorm_pulumi_awsloadbalancercontroller/py.typed
jaxxstorm_pulumi_awsloadbalancercontroller.egg-info/PKG-INFO
jaxxstorm_pulumi_awsloadbalancercontroller.egg-info/SOURCES.txt
jaxxstorm_pulumi_awsloadbalancercontroller.egg-info/dependency_links.txt
jaxxstorm_pulumi_awsloadbalancercontroller.egg-info/not-zip-safe
jaxxstorm_pulumi_awsloadbalancercontroller.egg-info/requires.txt
jaxxstorm_pulumi_awsloadbalancercontroller.egg-info/top_level.txt