Metadata-Version: 2.1
Name: jaxxstorm-pulumi-awsloadbalancercontroller
Version: 0.0.2a1623692364
Summary: UNKNOWN
Home-page: UNKNOWN
License: UNKNOWN
Platform: UNKNOWN
